Metadata-Version: 2.1
Name: django-threaded-sync-to-async
Version: 1.0.4
Summary: Tools for replacing `sync_to_async` calls to `sync_to_async(thread_sensitive=False, executor=...)`, effectively allowing Django to make calls to database concurrently
Home-page: https://github.com/excitoon/django_threaded_sync_to_async
Author: Vladimir Chebotarev
Author-email: vladimir.chebotarev@gmail.com
License: MIT
Project-URL: Documentation, https://github.com/excitoon/django_threaded_sync_to_async/blob/master/README.md
Project-URL: Source, https://github.com/excitoon/django_threaded_sync_to_async
Project-URL: Tracker, https://github.com/excitoon/django_threaded_sync_to_async/issues
Keywords: django,asyncio,asgiref,sync_to_async
Platform: UNKNOWN
Classifier: Development Status :: 5 - Production/Stable
Classifier: Intended Audience :: Developers
Classifier: License :: OSI Approved :: MIT License
Classifier: Operating System :: OS Independent
Classifier: Programming Language :: Python :: 3 :: Only
Classifier: Programming Language :: Python :: 3.10
Classifier: Programming Language :: Python :: 3.11
Classifier: Programming Language :: Python :: 3.12
Classifier: Topic :: Software Development :: Libraries :: Python Modules
Classifier: Topic :: Software Development :: Version Control :: Git
Classifier: Topic :: Text Processing :: Filters
